{"id":"1a4c9537-8e55-4b17-9fb1-dd68efe8cb29","ingredients":[{"amount":600.0,"name":"poulet","unit":"g"},{"amount":400.0,"name":"patate douce","unit":"g"},{"amount":300.0,"name":"pomme de terre","unit":"g"},{"amount":20.0,"name":"lait de coco","unit":"cl"},{"amount":400.0,"name":"pulpe de tomates","unit":"g"},{"name":"curry"},{"amount":3.0,"name":"gousse d'ail"},{"amount":1.0,"name":"oignon"},{"name":"sel"},{"name":"poivre"}],"name":"Curry de patates douces au poulet","quantity":{"amount":4.0,"unit":"personne"},"steps":[{"step":"Mettre de l'huile d'olive avec l'ail, l'oignon, sel et curry et laisser dorer 5 minutes"},{"step":"Ajouter les dés de patates douce"},{"step":"Peler et hacher le Gimgembre, ajouter à la sauteuse"},{"step":"Faire colorer le poulet "},{"step":"Ajouter tomates concassée et lait de coco"},{"step":"Laisser mijoter 15 minutes à feu doux"}]}